synthetmic_cli/__init__.py
synthetmic_cli/cli.py
synthetmic_cli/commands.py
synthetmic_cli/shared.py
synthetmic_cli-0.1.0.dist-info/METADATA
synthetmic_cli-0.1.0.dist-info/WHEEL
synthetmic_cli-0.1.0.dist-info/entry_points.txt
synthetmic_cli-0.1.0.dist-info/licenses/LICENSE
synthetmic_cli-0.1.0.dist-info/RECORD
