Metadata-Version: 2.4
Name: synthetmic-cli
Version: 0.1.0
Summary: A CLI for generating synthetic Laguerre polycrystalline microstructures
Project-URL: homepage, https://github.com/synthetic-microstructures/synthetmic-cli
Project-URL: issues, https://github.com/synthetic-microstructures/synthetmic-cli/issues
Author-email: "R. O. Ibraheem" <ibraheem.abdulrasheed@gmail.com>, "D. P. Bourne" <D.Bourne@hw.ac.uk>, "S. M. Roper" <Steven.Roper@glasgow.ac.uk>
Maintainer-email: "R. O. Ibraheem" <ibraheem.abdulrasheed@gmail.com>, "D. P. Bourne" <D.Bourne@hw.ac.uk>, "S. M. Roper" <Steven.Roper@glasgow.ac.uk>
License-Expression: MIT
License-File: LICENSE
Classifier: Operating System :: OS Independent
Classifier: Programming Language :: Python
Classifier: Programming Language :: Python :: 3
Classifier: Programming Language :: Python :: 3.11
Classifier: Programming Language :: Python :: 3.12
Classifier: Programming Language :: Python :: 3.13
Requires-Python: >=3.11
Requires-Dist: click>=8.2.1
Requires-Dist: pandas>=2.3.1
Requires-Dist: pyfiglet>=1.0.3
Requires-Dist: synthetmic==0.1.4
